.gitignore
CHANGES.txt
README.txt
setup.cfg
setup.py
minitage/__init__.py
minitage.paste.extras.egg-info/PKG-INFO
minitage.paste.extras.egg-info/SOURCES.txt
minitage.paste.extras.egg-info/dependency_links.txt
minitage.paste.extras.egg-info/entry_points.txt
minitage.paste.extras.egg-info/namespace_packages.txt
minitage.paste.extras.egg-info/not-zip-safe
minitage.paste.extras.egg-info/requires.txt
minitage.paste.extras.egg-info/top_level.txt
minitage/paste/__init__.py
minitage/paste/instances/__init__.py
minitage/paste/instances/ssl.py
minitage/paste/instances/cas/__init__.py
minitage/paste/instances/cas/package-cas-release.sh
minitage/paste/instances/cas/wrapper.py
minitage/paste/instances/cas/template/bin/cas.bootstrap.jar_tmpl
minitage/paste/instances/cas/template/bin/cas.catalina-tasks.xml_tmpl
minitage/paste/instances/cas/template/bin/cas.catalina.bat_tmpl
minitage/paste/instances/cas/template/bin/cas.catalina.sh_tmpl
minitage/paste/instances/cas/template/bin/cas.commons-daemon.jar_tmpl
minitage/paste/instances/cas/template/bin/cas.cpappend.bat_tmpl
minitage/paste/instances/cas/template/bin/cas.digest.bat_tmpl
minitage/paste/instances/cas/template/bin/cas.digest.sh_tmpl
minitage/paste/instances/cas/template/bin/cas.jsvc.tar.gz_tmpl
minitage/paste/instances/cas/template/bin/cas.jsvc_tmpl
minitage/paste/instances/cas/template/bin/cas.service.bat_tmpl
minitage/paste/instances/cas/template/bin/cas.setclasspath.bat_tmpl
minitage/paste/instances/cas/template/bin/cas.setclasspath.sh_tmpl
minitage/paste/instances/cas/template/bin/cas.setenv.sh_tmpl
minitage/paste/instances/cas/template/bin/cas.shutdown.bat_tmpl
minitage/paste/instances/cas/template/bin/cas.shutdown.sh_tmpl
minitage/paste/instances/cas/template/bin/cas.startup.bat_tmpl
minitage/paste/instances/cas/template/bin/cas.startup.sh_tmpl
minitage/paste/instances/cas/template/bin/cas.tomcat-juli.jar_tmpl
minitage/paste/instances/cas/template/bin/cas.tomcat-native-1.1.16-src_tmpl
minitage/paste/instances/cas/template/bin/cas.tomcat-native.tar.gz_tmpl
minitage/paste/instances/cas/template/bin/cas.tomcat6.exe_tmpl
minitage/paste/instances/cas/template/bin/cas.tomcat6w.exe_tmpl
minitage/paste/instances/cas/template/bin/cas.tool-wrapper.bat_tmpl
minitage/paste/instances/cas/template/bin/cas.tool-wrapper.sh_tmpl
minitage/paste/instances/cas/template/bin/cas.version.bat_tmpl
