Metadata-Version: 1.0
Name: minitage.paste.extras
Version: 1.9
Summary: Extension for minitage.paste allowing users to have some server instaces configured on top of projects
Home-page: http://cheeseshop.python.org/pypi/minitage.paste.extras
Author: Mathieu Pasquet
Author-email: kiorky@cryptelium.net
License: BSD
Keywords: PasteScripts minitage
Platform: UNKNOWN
Classifier: Framework :: Django
Classifier: Framework :: Pylons
Classifier: Framework :: Paste
Classifier: Framework :: Plone
Classifier: Framework :: Zope2
Classifier: Framework :: Zope3
Classifier: Framework :: Buildout
Classifier: Intended Audience :: Developers
Classifier: License :: OSI Approved :: BSD License
Classifier: Topic :: Software Development :: Build Tools
Classifier: Topic :: Software Development :: Libraries :: Python Modules
